my_vector_db/__init__.py
my_vector_db/api/__init__.py
my_vector_db/api/routes.py
my_vector_db/api/schemas.py
my_vector_db/cli.py
my_vector_db/db/__init__.py
my_vector_db/db/my_vector_db.py
my_vector_db/domain/__init__.py
my_vector_db/domain/models.py
my_vector_db/filters/__init__.py
my_vector_db/filters/evaluator.py
my_vector_db/indexes/__init__.py
my_vector_db/indexes/base.py
my_vector_db/indexes/flat.py
my_vector_db/indexes/hnsw.py
my_vector_db/indexes/ivf.py
my_vector_db/main.py
my_vector_db/mcp/server.py
my_vector_db/py.typed
my_vector_db/sdk/README.md
my_vector_db/sdk/__init__.py
my_vector_db/sdk/client.py
my_vector_db/sdk/errors.py
my_vector_db/sdk/exceptions.py
my_vector_db/sdk/models.py
my_vector_db/serialization.py
my_vector_db/services/__init__.py
my_vector_db/services/document_service.py
my_vector_db/services/library_service.py
my_vector_db/services/search_service.py
my_vector_db/storage.py
my_vector_db-0.3.0.dist-info/WHEEL
my_vector_db-0.3.0.dist-info/entry_points.txt
my_vector_db-0.3.0.dist-info/METADATA
my_vector_db-0.3.0.dist-info/RECORD
