Metadata-Version: 2.3
Name: my-vector-db
Version: 0.3.0
Summary: A lightweight vector database built with Python
Author: Adam Shedivy
Author-email: Adam Shedivy <ajshedivyaj@gmail.com>
Requires-Dist: agno>=2.2.1
Requires-Dist: anthropic>=0.71.0
Requires-Dist: cohere>=5.19.0
Requires-Dist: dotenv>=0.9.9
Requires-Dist: fastapi>=0.119.1
Requires-Dist: fastmcp>=2.13.0.2
Requires-Dist: mcp>=1.20.0
Requires-Dist: numpy>=2.3.4
Requires-Dist: openai>=2.6.1
Requires-Dist: pydantic>=2.12.3
Requires-Dist: scikit-learn>=1.7.2
Requires-Dist: sqlalchemy>=2.0.44
Requires-Dist: uvicorn[standard]>=0.38.0
Requires-Dist: prompt-toolkit>=3.0.0 ; extra == 'cli'
Requires-Dist: rich>=13.0.0 ; extra == 'cli'
Requires-Python: >=3.13
Provides-Extra: cli
